betterpipe/__init__.py
betterpipe-0.1.5.dist-info/WHEEL
betterpipe-0.1.5.dist-info/METADATA
betterpipe-0.1.5.dist-info/RECORD
